cob_ai/__init__.py
cob_ai/client.py
cob_ai/models.py
cob_ai-0.1.5.dist-info/licenses/LICENSE
cob_ai-0.1.5.dist-info/METADATA
cob_ai-0.1.5.dist-info/WHEEL
cob_ai-0.1.5.dist-info/top_level.txt
cob_ai-0.1.5.dist-info/RECORD
