Metadata-Version: 2.4
Name: cob-ai
Version: 0.1.5
Summary: Python client for the COB SharePoint search
Author-email: Lennart Timmermans <lennart@vondr.ai>
License: MIT License
Project-URL: Homepage, https://github.com/vondr/cob-ai
Project-URL: Repository, https://github.com/vondr/cob-ai
Project-URL: Issues, https://github.com/vondr/cob-ai/issues
Keywords: sharepoint,search,api,client
Classifier: Development Status :: 4 - Beta
Classifier: Intended Audience :: Developers
Classifier: Programming Language :: Python :: 3
Classifier: Programming Language :: Python :: 3.8
Classifier: Programming Language :: Python :: 3.9
Classifier: Programming Language :: Python :: 3.10
Classifier: Programming Language :: Python :: 3.11
Classifier: Programming Language :: Python :: 3.12
Requires-Python: >=3.9
License-File: LICENSE
Requires-Dist: attrs>=23.1.0
Requires-Dist: requests>=2.25.0
Requires-Dist: dotenv<0.10.0,>=0.9.9
Requires-Dist: build<2.0.0,>=1.3.0
Requires-Dist: twine<7.0.0,>=6.2.0
Dynamic: license-file
